crypt_me.py
ez_setup.py
setup.py
crypt_me.egg-info/PKG-INFO
crypt_me.egg-info/SOURCES.txt
crypt_me.egg-info/dependency_links.txt
crypt_me.egg-info/top_level.txt