Metadata-Version: 1.0
Name: crypt-me
Version: 0.140
Summary: Caesar cipher with qt GUI
Home-page: UNKNOWN
Author: Martin Bednar
Author-email: martin.bednar@hotmail.sk
License: GNU GPL v3 license
Keywords: Caesar
Platform: UNKNOWN
